code_guardian/__init__.py
code_guardian/main.py
code_guardian/prompt.py
code_guardian-0.1.4.dist-info/LICENSE
code_guardian-0.1.4.dist-info/METADATA
code_guardian-0.1.4.dist-info/WHEEL
code_guardian-0.1.4.dist-info/RECORD
